MOAI_iplweb-2.0.0.dist-info/METADATA
MOAI_iplweb-2.0.0.dist-info/RECORD
MOAI_iplweb-2.0.0.dist-info/WHEEL
MOAI_iplweb-2.0.0.dist-info/entry_points.txt
MOAI_iplweb-2.0.0.dist-info/top_level.txt
moai/__init__.py
moai/database.py
moai/error.py
moai/example.py
moai/interfaces.py
moai/metadata.py
moai/oai.py
moai/server.py
moai/test.py
moai/tools.py
moai/utils.py
moai/wsgi.py
moai/metadata/__init__.py
moai/metadata/dare_didl.py
moai/metadata/didl.py
moai/metadata/mods.py
moai/metadata/oaidc.py
moai/provider/__init__.py
moai/provider/fedora.py
moai/provider/file.py
moai/provider/list.py
moai/provider/oai.py
