Metadata-Version: 2.1
Name: MOAI-iplweb
Version: 2.0.0
Summary: MOAI, A Open Access Server Platform for Institutional Repositories
Home-page: http://iplweb.pl/
Author: Michał Pasternak
Author-email: michal.dtz@gmail.com
License: BSD
Platform: UNKNOWN
Classifier: Development Status :: 5 - Production/Stable
Classifier: Programming Language :: Python
Classifier: License :: OSI Approved :: BSD License
Classifier: Topic :: Software Development :: Libraries :: Python Modules
Classifier: Environment :: Web Environment
Requires-Dist: pyoai
Requires-Dist: WSGIUtils
Requires-Dist: wsgi-intercept
Requires-Dist: webob
Requires-Dist: paste
Requires-Dist: pasteDeploy
Requires-Dist: pasteScript
Requires-Dist: sqlalchemy
Requires-Dist: wsgi-intercept
Requires-Dist: future
Requires-Dist: six
